utils_funcs/__init__.py
utils_funcs/functions.py
utils_funcs-0.1.0.dist-info/LICENSE
utils_funcs-0.1.0.dist-info/METADATA
utils_funcs-0.1.0.dist-info/WHEEL
utils_funcs-0.1.0.dist-info/RECORD
