Metadata-Version: 2.3
Name: utils_funcs
Version: 0.1.0
Summary: A collection of reusable functions.
License: MIT
Author: Tyrone José
Author-email: alt.tyronejose@gmail.com
Requires-Python: >=3.10
Classifier: License :: OSI Approved :: MIT License
Classifier: Programming Language :: Python :: 3
Classifier: Programming Language :: Python :: 3.10
Classifier: Programming Language :: Python :: 3.11
Classifier: Programming Language :: Python :: 3.12
Classifier: Programming Language :: Python :: 3.13
Requires-Dist: pytest (>=8.3.4,<9.0.0)
Requires-Dist: setuptools (>=75.8.0,<76.0.0)
